taigapy/__init__.py
taigapy/client.py
taigapy/consts.py
taigapy/custom_exceptions.py
taigapy/figshare.py
taigapy/taiga_api.py
taigapy/taiga_cache.py
taigapy/types.py
taigapy/utils.py
taigapy-3.3.5.data/scripts/taigaclient
taigapy-3.3.5.dist-info/METADATA
taigapy-3.3.5.dist-info/WHEEL
taigapy-3.3.5.dist-info/top_level.txt
taigapy-3.3.5.dist-info/RECORD
