Metadata-Version: 2.1
Name: taigapy
Version: 3.3.5
Summary: UNKNOWN
Home-page: UNKNOWN
Author: Remi Marenco
Author-email: rmarenco@broadinstitute.org
License: Creative Commons Attribution-Noncommercial-Share Alike license
Platform: UNKNOWN
Requires-Dist: requests
Requires-Dist: pandas (<2.0.0,>=1.0.0)
Requires-Dist: aiobotocore (==1.2.2)
Requires-Dist: boto3 (<1.16.53,>=1.16.0)
Requires-Dist: nest-asyncio (<2.0.0,>=1.5.1)
Requires-Dist: colorful
Requires-Dist: progressbar2 (<4.0.0,>=3.3.0)
Requires-Dist: pyarrow (>=3.0.0)
